actionai/__init__.py
actionai/exceptions.py
actionai/json_schema.py
actionai/types.py
actionai-0.0.7.dist-info/LICENSE
actionai-0.0.7.dist-info/WHEEL
actionai-0.0.7.dist-info/METADATA
actionai-0.0.7.dist-info/RECORD
