Metadata-Version: 2.1
Name: actionai
Version: 0.0.7
Summary: A small library to call local functions using openai function calling
Author: Amal Shaji
Author-email: amalshajid@gmail.com
Requires-Python: >=3.8,<4.0
Classifier: Programming Language :: Python :: 3
Classifier: Programming Language :: Python :: 3.8
Classifier: Programming Language :: Python :: 3.9
Classifier: Programming Language :: Python :: 3.10
Requires-Dist: openai (>=0.27.8,<0.28.0)
Requires-Dist: pydantic (>=2.0.2,<3.0.0)
